PIL/__init__.py
helloworld/__init__.py
nirza_helloworld-0.0.1.dist-info/METADATA
nirza_helloworld-0.0.1.dist-info/WHEEL
nirza_helloworld-0.0.1.dist-info/top_level.txt
nirza_helloworld-0.0.1.dist-info/RECORD
