Metadata-Version: 2.4
Name: nirza-helloworld
Version: 0.0.1
Summary: Demo package
Author: Nir Za
Requires-Python: >=3.8
